Metadata-Version: 2.4
Name: costscanner
Version: 1.0.0
Summary: A cloud cost and security scanner for Terraform files
Author-email: Luna <your-email@example.com>
License: MIT
Keywords: terraform,cloud,security,cost,scanner
Requires-Python: >=3.8
License-File: LICENSE
Dynamic: license-file
